uniproj_2024/__init__.py
uniproj_2024/uniprot.py
uniproj_2024/uniprot_collection.py
uniproj_2024-0.1.7.dist-info/METADATA
uniproj_2024-0.1.7.dist-info/WHEEL
uniproj_2024-0.1.7.dist-info/top_level.txt
uniproj_2024-0.1.7.dist-info/RECORD
