Metadata-Version: 2.1
Name: uniproj_2024
Version: 0.1.7
Summary: Ce projet a pour but la manipulation et l'analyse de données de protéines issues de la base de données Uniprot via l'implémentation de classes Python.
Author: Maya Givre, Thibaud Guiramand
Project-URL: Documentation, http://pedago-service.univ-lyon1.fr:2325/tguiramand/uniprot/-/blob/publish/README.md?ref_type=heads
Project-URL: Repository, http://pedago-service.univ-lyon1.fr:2325/tguiramand/uniprot/-/tree/publish?ref_type=heads
Keywords: uniprot,protein,gene
Requires-Python: >=3.8
Requires-Dist: matplotlib>=3.8
